drb/drivers/odata/__init__.py
drb/drivers/odata/_version.py
drb/drivers/odata/expression.py
drb/drivers/odata/factory.py
drb/drivers/odata/odata_node.py
drb/drivers/odata/odata_nodes.py
drb/drivers/odata/odata_services_nodes.py
drb/drivers/odata/odata_utils.py
drb/drivers/odata/query_builder.py
drb/exceptions/odata.py
drb/topics/odata/__init__.py
drb/topics/odata/cortex.yml
drb_driver_odata-1.3.3.dist-info/LICENCE.txt
drb_driver_odata-1.3.3.dist-info/METADATA
drb_driver_odata-1.3.3.dist-info/WHEEL
drb_driver_odata-1.3.3.dist-info/entry_points.txt
drb_driver_odata-1.3.3.dist-info/top_level.txt
drb_driver_odata-1.3.3.dist-info/RECORD
