Metadata-Version: 2.1
Name: drb-driver-odata
Version: 1.3.3
Summary: DRB OData CSC driver
Author: GAEL Systems
Author-email: drb-python@gael.fr
License: LGPLv3
Classifier: Programming Language :: Python :: 3.8
Classifier: License :: OSI Approved :: GNU Lesser General Public License v3 (LGPLv3)
Requires-Python: >=3.8
License-File: LICENCE.txt
Requires-Dist: drb ~=2.2.0
Requires-Dist: drb-driver-http ~=1.3.1
Requires-Dist: drb-driver-json ~=1.3.0
Requires-Dist: defusedxml >=0.7.1
Requires-Dist: shapely >=2.0.1
